siriushlacon/__init__.py
siriushlacon/application.py
siriushlacon/logging.py
siriushlacon/agilent4uhv/__init__.py
siriushlacon/agilent4uhv/agilent.py
siriushlacon/agilent4uhv/channel.py
siriushlacon/agilent4uhv/consts.py
siriushlacon/agilent4uhv/device.py
siriushlacon/agilent4uhv/device_main.py
siriushlacon/agilent4uhv/devices.py
siriushlacon/agilent4uhv/extended.py
siriushlacon/agilent4uhv/main.py
siriushlacon/agilent4uhv/overview.py
siriushlacon/agilent4uhv/parameters.py
siriushlacon/agilent4uhv/tree.py
siriushlacon/agilent4uhv/ui/channel.ui
siriushlacon/agilent4uhv/ui/device.ui
siriushlacon/agilent4uhv/ui/device_main.ui
siriushlacon/agilent4uhv/ui/disp.ui
siriushlacon/agilent4uhv/ui/main.ui
siriushlacon/agilent4uhv/ui/run.sh
siriushlacon/beaglebones/BBBread.py
siriushlacon/beaglebones/__init__.py
siriushlacon/beaglebones/consts.py
siriushlacon/beaglebones/main.py
siriushlacon/beaglebones/models.py
siriushlacon/beaglebones/ui/configBBB.ui
siriushlacon/beaglebones/ui/infoBBB.ui
siriushlacon/beaglebones/ui/logsBBB.ui
siriushlacon/beaglebones/ui/main.ui
siriushlacon/beaglebones/ui/Resources/led-green.png
siriushlacon/beaglebones/ui/Resources/led-red.png
siriushlacon/countingpru/Overview.py
siriushlacon/countingpru/__init__.py
siriushlacon/countingpru/consts.py
siriushlacon/countingpru/main.py
siriushlacon/countingpru/pic/AfterBC.png
siriushlacon/countingpru/pic/BeforeBC.png
siriushlacon/countingpru/pic/CNPEM.png
siriushlacon/countingpru/pic/lnlsLogo.png
siriushlacon/countingpru/ui/layout_overview.ui
siriushlacon/countingpru/ui/main.ui
siriushlacon/countingpru/ui/overview.ui
siriushlacon/danfysik/__init__.py
siriushlacon/danfysik/consts.py
siriushlacon/danfysik/main.py
siriushlacon/danfysik/ui/main.ui
siriushlacon/epics/__init__.py
siriushlacon/epics/alarm.py
siriushlacon/epics/pv.py
siriushlacon/epicstel/__init__.py
siriushlacon/epicstel/aux_dialogs.py
siriushlacon/epicstel/consts.py
siriushlacon/epicstel/main.py
siriushlacon/epicstel/models.py
siriushlacon-2.7.2.dist-info/LICENSE
siriushlacon-2.7.2.dist-info/METADATA
siriushlacon-2.7.2.dist-info/WHEEL
siriushlacon-2.7.2.dist-info/entry_points.txt
siriushlacon-2.7.2.dist-info/top_level.txt
siriushlacon-2.7.2.dist-info/RECORD
