Metadata-Version: 2.1
Name: siriushlacon
Version: 2.7.2
Summary: Client Applications for Sirius
Home-page: https://github.com/lnls-sirius/pydm-opi/
Download-URL: https://github.com/lnls-sirius/pydm-opi
Author: Claudio F. Carneiro
License: GNU GPLv3
Project-URL: Changelog, https://github.com/lnls-sirius/pydm-opi/
Classifier: Intended Audience :: Science/Research
Classifier: Operating System :: OS Independent
Classifier: Programming Language :: Python :: 3 :: Only
Classifier: Programming Language :: Python :: 3
Classifier: Programming Language :: Python :: 3.6
Classifier: Programming Language :: Python :: 3.7
Classifier: Programming Language :: Python :: 3.8
Classifier: Programming Language :: Python :: 3.9
Classifier: Programming Language :: Python
Classifier: Topic :: Scientific/Engineering
Requires-Python: >=3.6
License-File: LICENSE
Requires-Dist: PyQt5 (==5.12.3)
Requires-Dist: conscommon (==0.1.4)
Requires-Dist: matplotlib (>=3.3.2)
Requires-Dist: pymongo (>=3.11.4)
Requires-Dist: pydm (<=1.10.4,>=1.10.1)
Requires-Dist: pyepics (>=3.4.1)
Requires-Dist: python-dateutil (>=2.8.1)
Requires-Dist: pytz (>=2020.1)
Requires-Dist: qtpy (==1.9.0)
Requires-Dist: redis (>=3.5.0)
Requires-Dist: urllib3 (>=1.26.5)
Requires-Dist: siriuspy (>=2.33.1)
